zpyval/__init__.py
zpyval/validator.py
zpyval/value.py
zpyval-0.1.0.dist-info/METADATA
zpyval-0.1.0.dist-info/WHEEL
zpyval-0.1.0.dist-info/RECORD
