Metadata-Version: 2.1
Name: zpyval
Version: 0.1.0
Summary: A package for a domain-centric predefined set of value objects.
Author: zathazass
Author-email: sathananthanit15@gmail.com
Requires-Python: >=3.9,<4.0
Classifier: Programming Language :: Python :: 3
Classifier: Programming Language :: Python :: 3.9
Classifier: Programming Language :: Python :: 3.10
Classifier: Programming Language :: Python :: 3.11
Classifier: Programming Language :: Python :: 3.12
